marquez/__init__.py
marquez/dataset.py
marquez/models.py
marquez/utils.py
marquez/provider/__init__.py
marquez/provider/bigquery.py
marquez/schema/__init__.py
marquez/sql/__init__.py
marquez/sql/parser.py
marquez_integration_common-0.16.1.dist-info/METADATA
marquez_integration_common-0.16.1.dist-info/WHEEL
marquez_integration_common-0.16.1.dist-info/top_level.txt
marquez_integration_common-0.16.1.dist-info/RECORD
